odoo/addons/mrp_production_note/README.rst
odoo/addons/mrp_production_note/__init__.py
odoo/addons/mrp_production_note/__manifest__.py
odoo/addons/mrp_production_note/i18n/de.po
odoo/addons/mrp_production_note/i18n/es.po
odoo/addons/mrp_production_note/i18n/es_MX.po
odoo/addons/mrp_production_note/i18n/fi.po
odoo/addons/mrp_production_note/i18n/fr.po
odoo/addons/mrp_production_note/i18n/gl.po
odoo/addons/mrp_production_note/i18n/hr.po
odoo/addons/mrp_production_note/i18n/hr_HR.po
odoo/addons/mrp_production_note/i18n/it.po
odoo/addons/mrp_production_note/i18n/lt.po
odoo/addons/mrp_production_note/i18n/mrp_production_note.pot
odoo/addons/mrp_production_note/i18n/nl_NL.po
odoo/addons/mrp_production_note/i18n/pt_BR.po
odoo/addons/mrp_production_note/i18n/ro.po
odoo/addons/mrp_production_note/i18n/sl.po
odoo/addons/mrp_production_note/i18n/tr.po
odoo/addons/mrp_production_note/i18n/tr_TR.po
odoo/addons/mrp_production_note/i18n/vi_VN.po
odoo/addons/mrp_production_note/i18n/zh_CN.po
odoo/addons/mrp_production_note/models/__init__.py
odoo/addons/mrp_production_note/models/mrp_production.py
odoo/addons/mrp_production_note/readme/CONTRIBUTORS.rst
odoo/addons/mrp_production_note/readme/DESCRIPTION.rst
odoo/addons/mrp_production_note/readme/USAGE.rst
odoo/addons/mrp_production_note/static/description/icon.png
odoo/addons/mrp_production_note/static/description/index.html
odoo/addons/mrp_production_note/views/mrp_production_view.xml
odoo13_addon_mrp_production_note-13.0.1.0.1.dev9.dist-info/METADATA
odoo13_addon_mrp_production_note-13.0.1.0.1.dev9.dist-info/WHEEL
odoo13_addon_mrp_production_note-13.0.1.0.1.dev9.dist-info/top_level.txt
odoo13_addon_mrp_production_note-13.0.1.0.1.dev9.dist-info/RECORD
